WeightedLDA/WeightedLDA.py
WeightedLDA/__init__.py
WeightedLDA-0.0.1.dist-info/LICENSE
WeightedLDA-0.0.1.dist-info/METADATA
WeightedLDA-0.0.1.dist-info/WHEEL
WeightedLDA-0.0.1.dist-info/top_level.txt
WeightedLDA-0.0.1.dist-info/RECORD
