Metadata-Version: 2.1
Name: WeightedLDA
Version: 0.0.1
Summary: Linear discriminant analysis with weights associated with each observation
Home-page: https://github.com/ptlake/WeightedLDA
Author: REX
Author-email: ptlakejr@gmail.com
Classifier: Programming Language :: Python :: 3
Classifier: License :: OSI Approved :: MIT License
Classifier: Operating System :: OS Independent
Requires-Python: >=3.7
License-File: LICENSE
